LICENSE.txt
README.md
setup.cfg
setup.py
phytorch/__init__.py
phytorch/math.py
phytorch/meta.py
phytorch.egg-info/PKG-INFO
phytorch.egg-info/SOURCES.txt
phytorch.egg-info/dependency_links.txt
phytorch.egg-info/requires.txt
phytorch.egg-info/top_level.txt
phytorch/constants/__init__.py
phytorch/constants/astro.py
phytorch/constants/codata.py
phytorch/constants/constant.py
phytorch/cosmology/__init__.py
phytorch/cosmology/components.py
phytorch/cosmology/core.py
phytorch/cosmology/module.py
phytorch/cosmology/utils.py
phytorch/cosmology/_research/ellip.py
phytorch/cosmology/_research/fit.py
phytorch/cosmology/_research/nn.py
phytorch/cosmology/drivers/__init__.py
phytorch/cosmology/drivers/_analytic_base.py
phytorch/cosmology/drivers/abstract.py
phytorch/cosmology/drivers/analytic.py
phytorch/cosmology/drivers/analytic_diff.py
phytorch/cosmology/drivers/odeint.py
phytorch/cosmology/special/__init__.py
phytorch/cosmology/special/concrete.py
phytorch/cosmology/special/decdm.py
phytorch/cosmology/special/flat.py
phytorch/distributions/__init__.py
phytorch/extensions/__init__.py
phytorch/extensions/elliptic.pyi
phytorch/extensions/roots.pyi
phytorch/extensions/special.pyi
phytorch/extensions/_algorithms/__init__.py
phytorch/extensions/_algorithms/common.py
phytorch/extensions/_algorithms/deta1.py
phytorch/extensions/_algorithms/elliptic.py
phytorch/extensions/_algorithms/gamma.py
phytorch/extensions/_algorithms/hyper.py
phytorch/extensions/_algorithms/meijerg.py
phytorch/extensions/_algorithms/polygamma.py
phytorch/extensions/_algorithms/roots.py
phytorch/interpolate/Linear1dInterpolator.py
phytorch/interpolate/LinearNDGridInterpolator.py
phytorch/interpolate/__init__.py
phytorch/interpolate/abc.py
phytorch/interpolate/splines.py
phytorch/quantities/__init__.py
phytorch/quantities/delegating.py
phytorch/quantities/dimspec.py
phytorch/quantities/quantity.py
phytorch/quantities/signatures.py
phytorch/quantities/tensor_quantity.py
phytorch/ragged/__init__.py
phytorch/ragged/ragged_old.py
phytorch/roots/__init__.py
phytorch/special/ellip.py
phytorch/special/ellipr.py
phytorch/special/elliptic.py
phytorch/special/gamma.py
