Metadata-Version: 2.1
Name: phytorch
Version: 0.0.42.0
Summary: Utilities for computational physics with PyTorch
Author: Kosio Karchev
Author-email: kosiokarchev@gmail.com
License: GPLv3
Project-URL: GitHub, https://github.com/kosiokarchev/phytorch
Classifier: License :: OSI Approved :: GNU General Public License v3 (GPLv3)
Classifier: Programming Language :: Python :: 3
Classifier: Programming Language :: Python :: 3.9
Classifier: Programming Language :: Python :: 3.10
Classifier: Intended Audience :: Science/Research
Classifier: Typing :: Typed
Requires-Python: >=3.9
Provides-Extra: testing
Provides-Extra: interop
Provides-Extra: odeint
License-File: LICENSE.txt
